{
  "feature": "wythers:vegetation/configured_random_patch/tall_tulips",
  "placement": [
    {
      "chance": 2,
      "type": "minecraft:rarity_filter"
    },
    {
      "type": "minecraft:in_square"
    },
    {
      "type": "minecraft:heightmap",
      "heightmap": "MOTION_BLOCKING_NO_LEAVES"
    },
    {
      "type": "minecraft:block_predicate_filter",
      "predicate": {
        "type": "minecraft:would_survive",
        "state": {
          "Name": "minecraft:fern"
        }
      }
    },
    {
      "type": "minecraft:biome"
    }
  ]
}
